{"columns":"1","palette_base":"DecoTile","palettes":"{\n\"DecoTile\": [\"Jungle\"],\n\"DecoTileGreen\": [\"Jungle\"]\n}","sheet_size":"Vector2i(80, 32)","source_path":"res://Assets/Sprites/Tilesets/Deco/JungleDecoLL.png","tiles":"{\nVector2(0, 16): {\n\"flip_h\": false,\n\"flip_v\": false,\n\"index\": 446\n},\nVector2(0, 24): {\n\"flip_h\": false,\n\"flip_v\": false,\n\"index\": 446\n},\nVector2(8, 16): {\n\"flip_h\": false,\n\"flip_v\": false,\n\"index\": 447\n},\nVector2(8, 24): {\n\"flip_h\": false,\n\"flip_v\": false,\n\"index\": 447\n},\nVector2(48, 16): {\n\"flip_h\": false,\n\"flip_v\": false,\n\"index\": 446\n},\nVector2(48, 24): {\n\"flip_h\": false,\n\"flip_v\": false,\n\"index\": 446\n},\nVector2(56, 16): {\n\"flip_h\": false,\n\"flip_v\": false,\n\"index\": 447\n},\nVector2(56, 24): {\n\"flip_h\": false,\n\"flip_v\": false,\n\"index\": 447\n}\n}"}
