{
	"palettes": {
		"default": [
			"00000000",
			"FFd9b2",
			"c77f3e",
			"416f71"
		],
		"DefaultNight": [
			"00000000",
			"662b17",
			"3d1a0e",
			"000000"
		],
		"Underground": [
			"00000000",
			"1f1f1f",
			"98b6ad",
			"165966"
		],
		"Castle": [
			"00000000",
			"797979",
			"ffffff",
			"bcbcbc"
		],
		"Underwater": [
			"00000000",
			"1f1f1f",
			"b5ffbd",
			"21ad10"
		],
		"Desert": [
			"00000000",
			"e4c8be",
			"ba6111",
			"d9a07a"
		],
		"DesertNight": [
			"00000000",
			"662b17",
			"ba6111",
			"000000"
		],
		"Jungle": [
			"00000000",
			"9f571b",
			"9f571b",
			"10434c"
		],
		"JungleNight": [
			"00000000",
			"1f1f1f",
			"ffb762",
			"ba6111"
		],
		"Snow": [
			"00000000",
			"dcdcff",
			"bcbcf0",
			"5c67bc"
		],
		"SnowNight": [
			"00000000",
			"5c67bc",
			"4240a7",
			"000000"
		],
		"Volcano": [
			"00000000",
			"1f1f1f",
			"ff8d00",
			"7c1d08"
		],
		"Autumn": [
			"00000000",
			"f9c19d",
			"c77f3e",
			"662900"
		],
		"AutumnNight": [
			"00000000",
			"662b17",
			"3d1a0e",
			"000000"
		],
		"Beach": [
			"00000000",
			"a2330f",
			"ffd9b2",
			"ffa044"
		],
		"Mountain": [
			"00000000",
			"1f1f1f",
			"c5c5c5",
			"676767"
		],
		"Space": [
			"00000000",
			"1f1f1f",
			"a8a3d9",
			"585f80"
		],
		"Bonus": [
			"00000000",
			"490047",
			"FFD9B2",
			"A176A3"
		]
	}
}
